essentials/__init__.py
essentials/caching.py
essentials/diagnostics.py
essentials/exceptions.py
essentials/folders.py
essentials/json.py
essentials/meta.py
essentials/py.typed
essentials/registry.py
essentials/secrets.py
essentials/decorators/__init__.py
essentials/decorators/logs.py
essentials/decorators/retry.py
essentials/typesutils/__init__.py
essentials/typesutils/dateutils.py
essentials/typesutils/timeutils.py
essentials-1.1.7.dist-info/METADATA
essentials-1.1.7.dist-info/WHEEL
essentials-1.1.7.dist-info/licenses/LICENSE
essentials-1.1.7.dist-info/RECORD
