Metadata-Version: 2.4
Name: essentials
Version: 1.1.7
Summary: General purpose classes and functions
Project-URL: homepage, https://github.com/Neoteroi/essentials
Author-email: Roberto Prevato <roberto.prevato@gmail.com>
License: MIT License
License-File: LICENSE
Keywords: core,utilities
Classifier: Development Status :: 5 - Production/Stable
Classifier: License :: OSI Approved :: MIT License
Classifier: Operating System :: OS Independent
Classifier: Programming Language :: Python :: 3
Classifier: Programming Language :: Python :: 3.9
Classifier: Programming Language :: Python :: 3.10
Classifier: Programming Language :: Python :: 3.11
Classifier: Programming Language :: Python :: 3.12
Classifier: Programming Language :: Python :: 3.13
